GUIAS/Guia 9/855926-Caua_Costa_Alves/Codigos/Verilog/v/Guia-0901.v
// ------------------------- 
// Guia_0901.v 
// Pulse and Trigger Generator 
// Nome: Cauã Costa Alves 
// Matricula: 855926
// ------------------------- 

module pulse_generator ( output pulse );
    reg pulse;
    
    initial begin : start
        pulse = 1'b0; 
    end // start

    always begin : pulse_gen 
        #25 pulse = 1'b1; 
        #25 pulse = 1'b0; 
    end // pulse_gen
endmodule // pulse_generator

module trigger_generator ( output trigger );
    reg trigger;
    
    initial begin : start
        trigger = 1'b0; 
    end // start

    always begin : trigger_gen 
        #100 trigger = 1'b1; 
        #10 trigger = 1'b0; 
        #90 trigger = 1'b1; 
        #10 trigger = 1'b0; 
    end // trigger_gen
endmodule // trigger_generator

module Guia_0901; 
    wire pulse; 
    wire trigger; 
    
    pulse_generator PG1 ( pulse ); 
    trigger_generator TG1 ( trigger ); 
    
    initial begin : main 
        $dumpfile ( "Guia_0901.vcd" ); 
        $dumpvars; 
        #500 $finish; 
    end // main
endmodule // Guia_0901

GUIAS/Guia 9/855926-Caua_Costa_Alves/Codigos/Verilog/vcd/Guia_0901.vcd
$date
	Friday Setember 11:24:22 2024
$end
$version
	Icarus Verilog
$end
$timescale
	1s
$end
$scope module Guia_0901 $end
$var wire 1 ! pulse $end
$var wire 1 " trigger $end
$scope module PG1 $end
$var reg 1 ! pulse $end
$scope begin pulse_gen $end
$upscope $end
$scope begin start $end
$upscope $end
$upscope $end
$scope module TG1 $end
$var reg 1 " trigger $end
$scope begin trigger_gen $end
$upscope $end
$upscope $end
$upscope $end
$scope begin main $end
$upscope $end
$upscope $end
$enddefinitions $end
$comment Show the parameter values. $end
$dumpall
$end
#0
$dumpvars
0!
0"
$end
#25
1!
#50
0!
#75
1!
#100
0"
#110
1"
#120
0"
#190
1"
#200
0"
#250
1!
#275
0!
