GUIAS/Guia 9/855926-Caua_Costa_Alves/Codigos/Verilog/clock.v
// ------------------------- 
// Clock.v
// Clock Generator
// Nome: Cauã Costa Alves 
// Matricula: 855926
// ------------------------- 

module clock ( output clk ); 
    reg clk;
    
    initial begin : start
    clk = 1'b0; 
    end // start

    always begin : clock 
        #12 clk = ~clk; 
    end // clock
endmodule // clock ( )

GUIAS/Guia 9/855926-Caua_Costa_Alves/Codigos/Verilog/v/Guia-0903.v
// ------------------------- 
// Guia_0903.v
// Pulse Generator with Frequency 1/3 of the Clock 
// Nome: Cauã Costa Alves 
// Matricula: 855926
// ------------------------- 

`include "clock.v"

module pulse ( signal, clock ); 
    input  clock; 
    output signal; 
    reg    signal; 
    
    always @ ( posedge clock ) 
    begin : pulse_gen
        signal = 1'b1; 
        #12 signal = 1'b0; 
        #12 signal = 1'b1; 
        #12 signal = 1'b0; 
    end // pulse_gen
endmodule // pulse

module Guia_0903; 
    wire  clock; 
    clock clk ( clock ); 
    
    wire  p; 
    pulse pls ( p, clock ); 
    
    initial begin : main 
        $dumpfile ( "Guia_0903.vcd" ); 
        $dumpvars ( 1, clock, p ); 
        
        #480 $finish; 
    end // main
endmodule // Guia_0903

GUIAS/Guia 9/855926-Caua_Costa_Alves/Codigos/Verilog/vcd/Guia-0903.vcd
$date
	Sat Sep 29 12:45:13 2024
$end
$version
	Icarus Verilog
$end
$timescale
	1s
$end
$scope module Guia_0903 $end
$var wire 1 ! clock $end
$upscope $end
$scope module Guia_0903 $end
$var wire 1 " p $end
$upscope $end
$enddefinitions $end
$comment Show the parameter values. $end
$dumpall
$end
#0
$dumpvars
0"
0!
$end
#12
1"
#24
0"
#36
1"
#48
0"
#60
1"
#72
0"
#84
1"
#96
0"
#108
1"
#120
0"
#132
1"
#144
0"
#156
1"
#168
0"
#180
1"
#192
0"
#204
1"
#216
0"
#228
1"
#240
0"
#252
1"
#264
0"
#276
1"
#288
0"
#300
1"
#312
0"
#324
1"
#336
0"
#348
1"
#360
0"
#372
1"
#384
0"
#396
1"
#408
0"
#420
1"
#432
0"
#444
1"
#456
0"
#468
1"
